core.v
module Core #(
    parameter BOOT_ADDRESS = 32'h00000000
)(
    // Control signal
    input wire clk,
    // input wire halt,
    input wire rst_n,

    // Memory BUS
    // input  wire ack_i,
    output reg        rd_en_o,
    output reg        wr_en_i,
     // output wire [3:0]  byte_enable,
    input  wire [31:0] data_i,
    output reg [31:0] addr_o,
    output reg [31:0] data_o
);

    reg [31:0] regfile [0:31];
    reg [31:0] pc;
    reg [3:0]  state;

    reg [31:0] instr;
    reg [31:0] sw_target;
    reg [31:0] sw_data;

    localparam FETCH = 0, DECODE = 1, EXEC = 2, WRITE_SW = 3, WAIT_SW = 4, LOAD_WAIT = 5, DONE = 6;

    always @(posedge clk or negedge rst_n) begin
        if (!rst_n) begin
            pc <= BOOT_ADDRESS;
            state <= FETCH;
            wr_en_i <= 0;
            rd_en_o <= 0;
            addr_o <= 0;
            data_o <= 0;

            regfile[0] <= 0;
            regfile[5] <= 0;
        end else begin
            regfile[0] <= 0;

            case (state)
                FETCH: begin
                    addr_o <= pc;
                    rd_en_o <= 1;
                    state <= DECODE;
                end

                DECODE: begin
                    rd_en_o <= 0;
                    instr <= data_i;
                    pc <= pc + 4;
                    state <= EXEC;
                end

                EXEC: begin
                    case (instr[6:0])
                        7'b0010011: begin // ADDI, SRLI
                            if (instr[14:12] == 3'b000) begin // ADDI
                                regfile[instr[11:7]] <= {{20{instr[31]}}, instr[31:20]};
                            end else if (instr[14:12] == 3'b101) begin // SRLI
                                regfile[instr[11:7]] <= regfile[instr[19:15]] >> instr[24:20];
                            end
                            state <= FETCH;
                        end

                        7'b0110011: begin // ADD, XOR
                            case (instr[14:12])
                                3'b000: regfile[instr[11:7]] <= regfile[instr[19:15]] + regfile[instr[24:20]];
                                3'b100: regfile[instr[11:7]] <= regfile[instr[19:15]] ^ regfile[instr[24:20]];
                            endcase
                            state <= FETCH;
                        end

                        7'b0100011: begin // SW
                            sw_target <= regfile[instr[19:15]] + {{20{instr[31]}}, instr[31:25], instr[11:7]};
                            sw_data <= regfile[instr[24:20]];
                            state <= WRITE_SW;
                        end

                        7'b0000011: begin // LW
                            addr_o <= regfile[instr[19:15]] + {{20{instr[31]}}, instr[31:20]};
                            rd_en_o <= 1;
                            state <= LOAD_WAIT;
                        end

                        7'b0110111: begin // LUI
                            regfile[instr[11:7]] <= {instr[31:12], 12'b0};
                            state <= FETCH;
                        end

                        7'b0010111: begin // AUIPC
                            regfile[instr[11:7]] <= pc - 4 + {instr[31:12], 12'b0};
                            state <= FETCH;
                        end

                        7'b1101111: begin // JAL
                            regfile[instr[11:7]] <= pc;
                            pc <= pc - 4 + {{12{instr[31]}}, instr[19:12], instr[20], instr[30:21], 1'b0};
                            state <= FETCH;
                        end

                        7'b1100111: begin // JALR
                            regfile[instr[11:7]] <= pc;
                            pc <= (regfile[instr[19:15]] + {{20{instr[31]}}, instr[31:20]}) & ~1;
                            state <= FETCH;
                        end

                        7'b1100011: begin // BEQ
                            if (regfile[instr[19:15]] == regfile[instr[24:20]]) begin
                                pc <= pc - 4 + {{20{instr[31]}}, instr[7], instr[30:25], instr[11:8], 1'b0};
                            end
                            state <= FETCH;
                        end

                        default: begin
                            state <= FETCH;
                        end
                    endcase
                end

                WRITE_SW: begin
                    addr_o <= sw_target;
                    data_o <= sw_data;
                    wr_en_i <= 1;
                    state <= WAIT_SW;
                end

                WAIT_SW: begin
                    wr_en_i <= 0;
                    state <= FETCH;
                end

                LOAD_WAIT: begin
                    rd_en_o <= 0;
                    regfile[instr[11:7]] <= data_i;
                    state <= FETCH;
                end

                DONE: begin
                end
            endcase
        end
    end

endmodule

memory.v
module Memory #(
    parameter MEMORY_FILE = "",
    parameter MEMORY_SIZE = 4096
)(
    input  wire        clk,
    input  wire        rd_en_i,
    input  wire        wr_en_i,
    input  wire [31:0] addr_i,
    input  wire [31:0] data_i,
    output wire [31:0] data_o,
    output wire        ack_o
);

    localparam DEPTH = MEMORY_SIZE / 4;
    reg [31:0] memory [0:DEPTH-1];

    initial begin
        if (MEMORY_FILE != "") begin
            $readmemh(MEMORY_FILE, memory);
        end
    end

    assign data_o = (rd_en_i && !wr_en_i) ? memory[addr_i[31:2]] : 32'b0;
    assign ack_o = 1'b1; 

    always @(posedge clk) begin
        if (wr_en_i) begin
            memory[addr_i >> 2] <= data_i;
        end
    end
endmodule

core_top.v
module core_top #(
    parameter MEMORY_FILE = "",
    parameter MEMORY_SIZE = 4096
)(
    input  wire clk,
    input  wire rst_n
);

    wire        rd_en;
    wire        wr_en;
    wire [31:0] addr;
    wire [31:0] data_in;
    wire [31:0] data_out;

    Memory #(
        .MEMORY_FILE(MEMORY_FILE),
        .MEMORY_SIZE(MEMORY_SIZE)
    ) mem (
        .clk(clk),
        .rd_en_i(rd_en),
        .wr_en_i(wr_en),
        .addr_i(addr),
        .data_i(data_out),
        .data_o(data_in),
        .ack_o() 
    );

    Core #(
        .BOOT_ADDRESS(32'h00000000)
    ) core (
        .clk(clk),
        .rst_n(rst_n),
        .rd_en_o(rd_en),
        .wr_en_i(wr_en),
        .data_i(data_in),
        .addr_o(addr),
        .data_o(data_out)
    );

endmodule

tb.v
`timescale 1ns/1ps

module tb();

reg clk = 0;
reg rst_n;
reg [31:0] expected_result;

reg [255:0] file_data [0:3];

always #1 clk = ~clk; // Clock generation

core_top #(
    .MEMORY_FILE("programa.txt") // Specify the memory file
) t (
    .clk(clk),
    .rst_n(rst_n)
);

integer i;
reg [7:0] counter = 0;

initial begin
    $dumpfile("saida.vcd");
    $dumpvars(0, tb);

    $readmemh("teste.txt", file_data); // Read the memory file

    $display("Programa executado:");
    $display("%s", file_data[0]);
    $display("%s", file_data[1]);
    $display("%s", file_data[2]);

    expected_result = file_data[3][31:0];

    rst_n = 0; // Reset the system
    #5;
    rst_n = 1; // Release reset
    
    while (tb.t.mem.data_o !== 32'hxxxxxxxx && counter <= 50) begin
        counter <= counter + 1;
        #2;
    end

    #2;


    if (tb.t.mem.memory[16/4] !== expected_result) begin
        $display("=== ERRO: Esperado %h na memória, obtido %h", expected_result, tb.t.mem.memory[16/4]);
    end else begin
        $display("=== OK: Obtido %h na memória", tb.t.mem.memory[16/4]);
    end

    $finish; // End simulation
end

endmodule

test/saida6.vcd
$date
	Sun Jul 20 19:47:02 2025
$end
$version
	Icarus Verilog
$end
$timescale
	1ps
$end
$scope module tb $end
$var reg 1 ! clk $end
$var reg 8 " counter [7:0] $end
$var reg 32 # expected_result [31:0] $end
$var reg 1 $ rst_n $end
$scope module t $end
$var wire 1 ! clk $end
$var wire 1 $ rst_n $end
$var wire 1 % wr_en $end
$var wire 1 & rd_en $end
$var wire 32 ' data_out [31:0] $end
$var wire 32 ( data_in [31:0] $end
$var wire 32 ) addr [31:0] $end
$var parameter 96 * MEMORY_FILE $end
$var parameter 32 + MEMORY_SIZE $end
$scope module core $end
$var wire 1 ! clk $end
$var wire 1 $ rst_n $end
$var wire 32 , data_i [31:0] $end
$var parameter 32 - BOOT_ADDRESS $end
$var parameter 32 . DECODE $end
$var parameter 32 / DONE $end
$var parameter 32 0 EXEC $end
$var parameter 32 1 FETCH $end
$var parameter 32 2 LOAD_WAIT $end
$var parameter 32 3 WAIT_SW $end
$var parameter 32 4 WRITE_SW $end
$var reg 32 5 addr_o [31:0] $end
$var reg 32 6 data_o [31:0] $end
$var reg 32 7 instr [31:0] $end
$var reg 32 8 pc [31:0] $end
$var reg 1 & rd_en_o $end
$var reg 4 9 state [3:0] $end
$var reg 32 : sw_data [31:0] $end
$var reg 32 ; sw_target [31:0] $end
$var reg 1 % wr_en_i $end
$upscope $end
$scope module mem $end
$var wire 1 < ack_o $end
$var wire 32 = addr_i [31:0] $end
$var wire 1 ! clk $end
$var wire 32 > data_i [31:0] $end
$var wire 1 & rd_en_i $end
$var wire 1 % wr_en_i $end
$var wire 32 ? data_o [31:0] $end
$var parameter 32 @ DEPTH $end
$var parameter 96 A MEMORY_FILE $end
$var parameter 32 B MEMORY_SIZE $end
$upscope $end
$upscope $end
$upscope $end
$enddefinitions $end
$comment Show the parameter values. $end
$dumpall
b1000000000000 B
b11100000111001001101111011001110111001001100001011011010110000100101110011101000111100001110100 A
b10000000000 @
b11 4
b100 3
b101 2
b0 1
b10 0
b110 /
b1 .
b0 -
b1000000000000 +
b11100000111001001101111011001110111001001100001011011010110000100101110011101000111100001110100 *
$end
#0
$dumpvars
b0 ?
b0 >
b0 =
1<
bx ;
bx :
b0 9
b0 8
bx 7
b0 6
b0 5
b0 ,
b0 )
b0 (
b0 '
0&
0%
0$
b0 #
b0 "
0!
$end
#1000
1!
#2000
0!
#3000
1!
#4000
0!
#5000
b100000000000001011100111 (
b100000000000001011100111 ,
b100000000000001011100111 ?
b1 9
1&
b1 "
1!
1$
#6000
0!
#7000
b0 (
b0 ,
b0 ?
b10 9
b100 8
b100000000000001011100111 7
0&
b10 "
1!
#8000
0!
#9000
b0 9
b1000 8
b11 "
1!
#10000
0!
#11000
b10100000100011 (
b10100000100011 ,
b10100000100011 ?
b1 9
1&
b1000 )
b1000 5
b1000 =
b100 "
1!
#12000
0!
#13000
b0 (
b0 ,
b0 ?
b10 9
b1100 8
b10100000100011 7
0&
b101 "
1!
#14000
0!
#15000
b11 9
b0 :
b10000 ;
b110 "
1!
#16000
0!
#17000
b100 9
1%
b10000 )
b10000 5
b10000 =
b111 "
1!
#18000
0!
#19000
b0 9
0%
b1000 "
1!
#20000
0!
#21000
bx (
bx ,
bx ?
b1 9
1&
b1100 )
b1100 5
b1100 =
b1001 "
1!
#22000
0!
#23000
b0 (
b0 ,
b0 ?
b10 9
b10000 8
bx 7
0&
1!
#24000
0!
#25000
b0 9
1!
